LICENSE
MANIFEST.in
README.md
README.rst
setup.py
django_highcharts.egg-info/PKG-INFO
django_highcharts.egg-info/SOURCES.txt
django_highcharts.egg-info/dependency_links.txt
django_highcharts.egg-info/not-zip-safe
django_highcharts.egg-info/requires.txt
django_highcharts.egg-info/top_level.txt
highcharts/__init__.py
highcharts/models.py
highcharts/tests.py
highcharts/utils.py
highcharts/static/js/highcharts/heatmap.js
highcharts/static/js/highcharts/highcharts-3d.js
highcharts/static/js/highcharts/highcharts-3d.src.js
highcharts/static/js/highcharts/highcharts-all.js
highcharts/static/js/highcharts/highcharts-more.js
highcharts/static/js/highcharts/highcharts-more.src.js
highcharts/static/js/highcharts/highcharts.js
highcharts/static/js/highcharts/highcharts.src.js
highcharts/static/js/highcharts/highstock.js
highcharts/static/js/highcharts/stock_exporting.js
highcharts/static/js/highcharts/technical-indicators.src.js
highcharts/static/js/highcharts/.fr-amL3gv/annotations.js
highcharts/static/js/highcharts/.fr-amL3gv/annotations.src.js
highcharts/static/js/highcharts/.fr-amL3gv/canvas-tools.js
highcharts/static/js/highcharts/.fr-amL3gv/canvas-tools.src.js
highcharts/static/js/highcharts/.fr-amL3gv/dark-blue.js
highcharts/static/js/highcharts/.fr-amL3gv/dark-green.js
highcharts/static/js/highcharts/.fr-amL3gv/data.js
highcharts/static/js/highcharts/.fr-amL3gv/data.src.js
highcharts/static/js/highcharts/.fr-amL3gv/exporting.js
highcharts/static/js/highcharts/.fr-amL3gv/exporting.src.js
highcharts/static/js/highcharts/.fr-amL3gv/funnel.js
highcharts/static/js/highcharts/.fr-amL3gv/funnel.src.js
highcharts/static/js/highcharts/.fr-amL3gv/gray.js
highcharts/static/js/highcharts/.fr-amL3gv/grid.js
highcharts/static/js/highcharts/.fr-amL3gv/highcharts-more.js
highcharts/static/js/highcharts/.fr-amL3gv/highcharts-more.src.js
highcharts/static/js/highcharts/.fr-amL3gv/highcharts.js
highcharts/static/js/highcharts/.fr-amL3gv/highcharts.src.js
highcharts/static/js/highcharts/.fr-amL3gv/skies.js
highcharts/static/js/highcharts/adapters/standalone-framework.js
highcharts/static/js/highcharts/adapters/standalone-framework.src.js
highcharts/static/js/highcharts/modules/canvas-tools.js
