Metadata-Version: 1.1
Name: django-highcharts
Version: 0.1.7
Summary: Django Highcharts helpers
Home-page: https://github.com/ernestoarbitrio/django-highcharts
Author: ernestoarbitrio
Author-email: ernesto.arbitrio@gmail.com
License: BSD Licence
Keywords: d,j,a,n,g,o, ,c,h,a,r,t, ,h,i,g,h,c,h,a,r,t,s, ,a,j,a,x, ,c,l,a,s,s, ,b,a,s,e,d, ,v,i,e,w,s
Platform: UNKNOWN
Classifier: Development Status :: 4 - Beta
Classifier: Environment :: Web Environment
Classifier: Framework :: Django
Classifier: Intended Audience :: Developers
Classifier: License :: OSI Approved :: BSD License
Classifier: Programming Language :: Python
Classifier: Programming Language :: Python :: 2.7
Classifier: Programming Language :: Python :: 3
